upend/__init__.py
upend/lib.py
upend/upend.py
upend/util.py
upend-0.0.1.dist-info/WHEEL
upend-0.0.1.dist-info/METADATA
upend-0.0.1.dist-info/RECORD
