Metadata-Version: 2.1
Name: upend
Version: 0.0.1
Summary: 
Author: Tomáš Mládek
Author-email: t@mldk.cz
Requires-Python: >=3.7,<4.0
Classifier: Programming Language :: Python :: 3
Classifier: Programming Language :: Python :: 3.7
Classifier: Programming Language :: Python :: 3.8
Classifier: Programming Language :: Python :: 3.9
Requires-Dist: requests (>=2.25.1,<3.0.0)
